myFirstPiPy/__init__.py
myFirstPiPy-0.0.3.dist-info/LICENSE
myFirstPiPy-0.0.3.dist-info/METADATA
myFirstPiPy-0.0.3.dist-info/WHEEL
myFirstPiPy-0.0.3.dist-info/top_level.txt
myFirstPiPy-0.0.3.dist-info/RECORD
