Metadata-Version: 2.1
Name: myFirstPiPy
Version: 0.0.3
Summary: My first PiP
Home-page: https://github.com/StudentESE/myFirstPiP
Author: Daniel Bunzendahl
Author-email: StudentDanBu@gmail.com
License: UNKNOWN
Platform: UNKNOWN
Classifier: Programming Language :: Python :: 3
Classifier: License :: OSI Approved :: MIT License
Classifier: Operating System :: OS Independent
